network_symmetry_core.cpython-310-x86_64-linux-gnu.so
network_symmetry/__init__.py
network_symmetry/symmetry.py
network_symmetry.libs/libgomp-a34b3233.so.1.0.0
network_symmetry-0.4.2.dist-info/LICENSE
network_symmetry-0.4.2.dist-info/METADATA
network_symmetry-0.4.2.dist-info/RECORD
network_symmetry-0.4.2.dist-info/top_level.txt
network_symmetry-0.4.2.dist-info/WHEEL
