Metadata-Version: 2.1
Name: network-symmetry
Version: 0.4.2
Summary: Library to compute accessibility and symmetry in networks
Home-page: https://github.com/ABenatti/network-accessibility
Author: Filipi N. Silva, Alexandre Benatti, Henrique F. Arruda
Author-email: filsilva@iu.edu, alexandre.benatti@usp.br, h.f.arruda@gmail.com
Classifier: Programming Language :: Python :: 3
Classifier: License :: OSI Approved :: MIT License
Classifier: Operating System :: MacOS :: MacOS X
Classifier: Operating System :: Microsoft :: Windows
Classifier: Operating System :: POSIX :: Linux
Classifier: Development Status :: 3 - Alpha
Classifier: Programming Language :: C
Classifier: Topic :: Scientific/Engineering :: Information Analysis
Classifier: Intended Audience :: Science/Research
Requires-Python: >=3.6
License-File: LICENSE
Requires-Dist: numpy >=1.18
Requires-Dist: scipy
